{
	"animations": [
		{
			"loop": false,
			"offsets": [
				110,
				-52
			],
			"anim": "singLEFT",
			"fps": 24,
			"name": "left",
			"indices": []
		},
		{
			"loop": true,
			"offsets": [
				-60,
				-80
			],
			"anim": "idle",
			"fps": 24,
			"name": "Idle",
			"indices": []
		},
		{
			"loop": false,
			"offsets": [
				24,
				26
			],
			"anim": "singUP",
			"fps": 24,
			"name": "up",
			"indices": []
		},
		{
			"loop": false,
			"offsets": [
				-1,
				-167
			],
			"anim": "singDOWN",
			"fps": 24,
			"name": "down",
			"indices": []
		},
		{
			"offsets": [
				10,
				5
			],
			"loop": false,
			"fps": 24,
			"anim": "singUP-alt",
			"indices": [],
			"name": "FrustScream"
		},
		{
			"loop": false,
			"offsets": [
				-100,
				-12
			],
			"anim": "singRIGHT",
			"fps": 24,
			"name": "right",
			"indices": []
		},
		{
			"offsets": [
				-27,
				-35
			],
			"indices": [],
			"fps": 24,
			"anim": "singDOWN-alt",
			"loop": false,
			"name": "laugh"
		}
	],
	"no_antialiasing": false,
	"image": "characters/exe",
	"position": [
		0,
		0
	],
	"healthicon": "sonicexe",
	"flip_x": false,
	"healthbar_colors": [
		0,
		85,
		142
	],
	"camera_position": [
		-10,
		110
	],
	"sing_duration": 4,
	"scale": 1
}