{
	"animations": [
		{
			"offsets": [
				-11,
				5
			],
			"loop": false,
			"fps": 24,
			"anim": "singRIGHT",
			"indices": [],
			"name": "Right"
		},
		{
			"offsets": [
				-6,
				-16
			],
			"loop": false,
			"fps": 24,
			"anim": "singDOWN",
			"indices": [],
			"name": "Down"
		},
		{
			"offsets": [
				-6,
				-8
			],
			"loop": false,
			"fps": 24,
			"anim": "singLEFT",
			"indices": [],
			"name": "Left"
		},
		{
			"offsets": [
				-6,
				26
			],
			"loop": false,
			"fps": 24,
			"anim": "singUP",
			"indices": [],
			"name": "Up"
		},
		{
			"loop": true,
			"offsets": [
				-10,
				-3
			],
			"anim": "idle",
			"fps": 11,
			"name": "idle",
			"indices": []
		}
	],
	"no_antialiasing": true,
	"image": "characters/starvedriendofuerte",
	"position": [
		1130,
		-20
	],
	"healthicon": "eggman",
	"flip_x": false,
	"healthbar_colors": [
		255,
		0,
		0
	],
	"camera_position": [
		-230,
		150
	],
	"sing_duration": 4,
	"scale": 1.5
}